{
  "hash": "fdd646cb",
  "configHash": "135df27c",
  "lockfileHash": "aa876fe8",
  "browserHash": "39acbd95",
  "optimized": {
    "react/jsx-dev-runtime": {
      "src": "../../node_modules/react/jsx-dev-runtime.js",
      "file": "react_jsx-dev-runtime.js",
      "fileHash": "c15a9854",
      "needsInterop": true
    },
    "react": {
      "src": "../../node_modules/react/index.js",
      "file": "react.js",
      "fileHash": "4a176ef6",
      "needsInterop": true
    },
    "react-dom/client": {
      "src": "../../node_modules/react-dom/client.js",
      "file": "react-dom_client.js",
      "fileHash": "619f9bae",
      "needsInterop": true
    },
    "react-router-dom": {
      "src": "../../node_modules/react-router-dom/dist/index.mjs",
      "file": "react-router-dom.js",
      "fileHash": "e9475458",
      "needsInterop": false
    },
    "react-bootstrap": {
      "src": "../../node_modules/react-bootstrap/esm/index.js",
      "file": "react-bootstrap.js",
      "fileHash": "61abd34a",
      "needsInterop": false
    },
    "axios": {
      "src": "../../node_modules/axios/index.js",
      "file": "axios.js",
      "fileHash": "ed6a6191",
      "needsInterop": false
    },
    "lucide-react": {
      "src": "../../node_modules/lucide-react/dist/esm/lucide-react.js",
      "file": "lucide-react.js",
      "fileHash": "c3da4479",
      "needsInterop": false
    },
    "@stomp/stompjs": {
      "src": "../../node_modules/@stomp/stompjs/esm6/index.js",
      "file": "@stomp_stompjs.js",
      "fileHash": "0f9fed7e",
      "needsInterop": false
    }
  },
  "chunks": {
    "chunk-R3E4LXVO": {
      "file": "chunk-R3E4LXVO.js"
    },
    "chunk-P6RTVJOB": {
      "file": "chunk-P6RTVJOB.js"
    },
    "chunk-G3PMV62Z": {
      "file": "chunk-G3PMV62Z.js"
    }
  }
}